pybacktestchain_options/__init__.py
pybacktestchain_options/api.py
pybacktestchain_options/blockchain/backtest.pkl
pybacktestchain_options/blockchain.py
pybacktestchain_options/broker.py
pybacktestchain_options/data_module.py
pybacktestchain_options/main.py
pybacktestchain_options/tests/__init__.py
pybacktestchain_options/tests/test_pybacktestchain_options.py
pybacktestchain_options/universal_backtest.py
pybacktestchain_options/utils.py
pybacktestchain_options-0.1.1.dist-info/LICENSE
pybacktestchain_options-0.1.1.dist-info/METADATA
pybacktestchain_options-0.1.1.dist-info/WHEEL
pybacktestchain_options-0.1.1.dist-info/RECORD
