Metadata-Version: 2.3
Name: pybacktestchain_options
Version: 0.1.1
Summary: A backtesting package for options
License: MIT
Author: Guillaume Touly
Requires-Python: >=3.10,<4.0
Classifier: License :: OSI Approved :: MIT License
Classifier: Programming Language :: Python :: 3
Classifier: Programming Language :: Python :: 3.10
Classifier: Programming Language :: Python :: 3.11
Classifier: Programming Language :: Python :: 3.12
Classifier: Programming Language :: Python :: 3.13
Requires-Dist: numba (>=0.60.0,<0.61.0)
Requires-Dist: pandas (>=2.2.3,<3.0.0)
Requires-Dist: pybacktestchain (>=0.2.1,<0.3.0)
Requires-Dist: typer[all] (>=0.15.1,<0.16.0)
Requires-Dist: yfinance (>=0.2.51,<0.3.0)
